subdivision_hole_filler/__init__.py
subdivision_hole_filler/_version.py
subdivision_hole_filler/hole_filler.py
subdivision_hole_filler-1.0.7.dist-info/LICENSE
subdivision_hole_filler-1.0.7.dist-info/METADATA
subdivision_hole_filler-1.0.7.dist-info/WHEEL
subdivision_hole_filler-1.0.7.dist-info/top_level.txt
subdivision_hole_filler-1.0.7.dist-info/RECORD
