Metadata-Version: 2.1
Name: subdivision-hole-filler
Version: 1.0.7
Summary: A python package to fill N-sided holes using combined subdivision schemes, based on Catmull-Clark subdivison.
Author-email: HUANG Lihao <huang-lihao@outlook.com>
Project-URL: Homepage, https://github.com/huang-lihao/subdivision-hole-filler
Project-URL: Bug Tracker, https://github.com/huang-lihao/subdivision-hole-filler/issues
Classifier: Programming Language :: Python :: 3
Classifier: License :: OSI Approved :: MIT License
Classifier: Operating System :: OS Independent
Requires-Python: >=3.7
License-File: LICENSE
Requires-Dist: matplotlib
Requires-Dist: numpy
Requires-Dist: scipy
